Workbook

Sheet Start Here
A1: Meta Ads Client OS
A2: Built from the Meta Ads Playbook (5 Sergio C / ADVT videos). One workbook per agency; duplicate checklist tabs per client.
A4: How to use
A5: 1. New client | B5: Duplicate 'New Client Checklist', rename it with the client name, work top to bottom. Fill 'Client Economics' first.
A6: 2. Existing client | B6: Duplicate 'Existing Client Audit'. Pull 30 days of Ads Manager + Shopify data into 'Weekly Tracker' to find the first leak.
A7: 3. Every week | B7: Follow 'Weekly Routine'. Add one row per client per week to 'Weekly Tracker'.
A8: 4. Every test | B8: Creative tests go in 'Creative Test Log' (auto verdict). Every stairway step goes in 'Stairway Test Log'.
A9: 5. Thresholds | B9: All benchmarks live in 'KPI Benchmarks' column D. Change them there and every flag updates.
A11: Legend
A12: Yellow cells | B12: Inputs you type or paste.
A13: White / black text | B13: Formulas. Don't overwrite.
A14: Green / amber / red fill | B14: Automatic flags: healthy / watch / problem.
A15: Row 1 of each log | B15: Example row with realistic values. Overwrite or delete it.
A17: Core rules
A18: Profit equation | B18: Revenue = (Spend ÷ CPC) × Conversion rate × AOV. Move one lever at a time.
A19: Stairway | B19: 1 Creative → 2 Copy → 3 Landing page → 4 Audience → 5 Scale. One variable per step.
A20: Diagnose | B20: Walk the funnel top-down; fix only the FIRST failing stage (Weekly Tracker column Z).
A21: Structure | B21: Ads live must match budget (~$30/day = 1–3 ads). 80–90% prospecting, 10–20% retargeting.
A22: Scale | B22: Only above scale-zone ROAS, in $10–20/day steps. Tests run beside the main campaigns, never inside.

Sheet New Client Checklist
A1: New Client Checklist
A2: Duplicate per client. Work top to bottom: each phase depends on the one above.
A3: Client: | D3: Progress: | E3: =IFERROR(COUNTIF(E6:E29,"Done")/(COUNTA(C6:C29)-COUNTIF(E6:E29,"N/A")),0)
A5: # | B5: Phase | C5: Task | D5: Standard / why | E5: Status | F5: Date done | G5: Owner | H5: Notes
A6: 1 | B6: A Economics & goals | C6: Fill Client Economics: AOV, product, fulfilment, fees | D6: Gives break-even CPA and ROAS. No launch without it. | E6: Not started
A7: 2 | B7: A Economics & goals | C7: Agree the goal: profit-first, growth-first or hybrid | D7: Target ROAS sits above break-even, never a vanity number (8x target can block growth that 3–5x funds). | E7: Not started
A8: 3 | B8: A Economics & goals | C8: Record LTV, repeat rate and maximum payback period | D8: Decides how far below break-even the first order may go. | E8: Not started
A9: 4 | B9: A Economics & goals | C9: Set daily budget and max ads live | D9: ~$30/day = 1–3 ads; $100–700 = 2–5 winners; $1,000+ = volume. | E9: Not started
A10: 5 | B10: A Economics & goals | C10: List AOV levers the store can offer | D10: Bundles, quantity breaks, free-shipping threshold, last-second add-on. | E10: Not started
A11: 6 | B11: B Tracking & setup | C11: Confirm the pixel on the site is the dataset selected in Ads Manager | D11: Use Meta Pixel Helper / data advisor; purchase event fires with value. | E11: Not started
A12: 7 | B12: B Tracking & setup | C12: Save the custom column preset | D12: Delivery, frequency, CPC (all), clicks (all), cost per link click, link clicks, content views, ATC, checkouts, purchases, cost per result, purchase value, ROAS, spend, budget, impressions, CTR (all), link CTR, CPM, video plays, 3s plays, ThruPlays. | E12: Not started
A13: 8 | B13: B Tracking & setup | C13: Build custom audiences | D13: Video viewers 50%, IG/FB engagers 365d, site visitors 30/180d, ATC 180d, purchasers 30/180/730d. | E13: Not started
A14: 9 | B14: B Tracking & setup | C14: Record the funnel baseline from Shopify | D14: Sessions, ATC rate, checkout rate, conversion rate. Walk checkout on a phone. | E14: Not started
A15: 10 | B15: C Research & creative | C15: Mine customer words | D15: Reviews, comments, tickets, surveys, Reddit, competitor reviews → what they want, what stops them, what they've tried. | E15: Not started
A16: 11 | B16: C Research & creative | C16: Write 3–5 one-sentence angles | D16: One problem per ad. List use-case personas (e.g. nursery, RV, trucker). | E16: Not started
A17: 12 | B17: C Research & creative | C17: Plan visual proof for every claim | D17: If it says 'fits under the desk', show it under the desk. | E17: Not started
... A29: 24 | B29: E Launch & scale | C29: Scale rule agreed with client | D29: Only above scale-zone ROAS, in $10–20/day steps. | E29: Not started

Sheet Existing Client Audit
A1: Existing Client Audit
A2: Duplicate per client. Finds the leaks before anything new is built.
A3: Client: | D3: Progress: | E3: =IFERROR(COUNTIF(E6:E28,"Done")/(COUNTA(C6:C28)-COUNTIF(E6:E28,"N/A")),0)
A5: # | B5: Phase | C5: Task | D5: Standard / why | E5: Status | F5: Date done | G5: Owner | H5: Notes
A6: 1 | B6: A Economics | C6: Fill Client Economics and compare actual ROAS with break-even | D6: Is the account really unprofitable, or just missing a vanity target? | E6: Not started
A7: 2 | B7: A Economics | C7: Check the goal is realistic | D7: Profit-first vs growth-first; scale zone above break-even × multiple. | E7: Not started
A8: 3 | B8: B Structure & spend | C8: Count active ads vs daily budget | D8: More ads than the budget supports = money spread thin. | E8: Not started
A9: 4 | B9: B Structure & spend | C9: Ad level, last 6–12 months, sorted by spend (not ROAS) | D9: What % of spend goes to the top 3 ads? Usually ~30% of ads drive the sales. | E9: Not started
A10: 5 | B10: B Structure & spend | C10: Build the cut list | D10: Meaningful spend and CPA consistently above target → off (e.g. $28 CPA vs $15 goal). | E10: Not started
A11: 6 | B11: B Structure & spend | C11: Build the 'shadow' retest list | D11: Low spend but strong link CTR / cheap CPM → into a capped creative test. | E11: Not started
A12: 7 | B12: B Structure & spend | C12: Are tests mixed into the money campaigns? | D12: Tests must run in separate campaigns. | E12: Not started
A13: 8 | B13: B Structure & spend | C13: Objective = Sales, optimisation = Purchase | D13: Add-to-cart or traffic optimisation finds non-buyers. | E13: Not started
A14: 9 | B14: B Structure & spend | C14: Budget split prospecting vs retargeting | D14: Target 80–90% / 10–20%. | E14: Not started
A15: 10 | B15: B Structure & spend | C15: Retargeting segmented with exclusions | D15: Middle excludes site visitors 180d + purchasers 730d; bottom excludes purchasers 30d. | E15: Not started
A16: 11 | B16: C Funnel | C16: Paste last 30 days into Weekly Tracker | D16: Column Z names the first leak. Fix only that one first. | E16: Not started
A17: 12 | B17: C Funnel | C17: Link clicks vs landing page views gap | D17: Large gap = speed, tracking, mobile. | E17: Not started
... A28: 23 | B28: G Plan | C28: Propose one AOV lever | D28: Bundle, quantity break or shipping threshold. | E28: Not started

Sheet Weekly Routine
A1: Weekly Routine
A2: Recurring cadence for every live client.
A3: Client: | D3: Progress: | E3: =IFERROR(COUNTIF(E6:E15,"Done")/(COUNTA(C6:C15)-COUNTIF(E6:E15,"N/A")),0)
A5: # | B5: Phase | C5: Task | D5: Standard / why | E5: Status | F5: Date done | G5: Owner | H5: Notes
A6: 1 | B6: A Weekly | C6: Add this week's row per client to Weekly Tracker | D6: Same day every week. | E6: Not started
A7: 2 | B7: A Weekly | C7: Act on the first leak only | D7: One change at a time, logged in Notes. | E7: Not started
A8: 3 | B8: A Weekly | C8: Update Creative Test Log; pause ads that hit the cap | D8: Promote winners, cut losers. | E8: Not started
A9: 4 | B9: A Weekly | C9: Cut ads with meaningful spend above target CPA | D9: Every ad earns its keep. | E9: Not started
A10: 5 | B10: A Weekly | C10: Fatigue check on winners | D10: Frequency, CPM, CTR trend. | E10: Not started
A11: 6 | B11: A Weekly | C11: Budget step decision | D11: Above scale zone → +$10–20/day or a new audience; below break-even → hold. | E11: Not started
A12: 7 | B12: B Monthly | C12: Refresh Client Economics | D12: Costs, AOV, LTV change. | E12: Not started
A13: 8 | B13: B Monthly | C13: Brief the next creative batch from winners | D13: New hook / creator / format / offer / message / angle; one change each. | E13: Not started
A14: 9 | B14: B Monthly | C14: Review Stairway Test Log learnings with the client | D14: What we tested, what won, what's next. | E14: Not started
A15: 10 | B15: B Monthly | C15: Check if a market is topping out (~$500–700/day) | D15: Plan broader creative or a new persona bucket. | E15: Not started

Sheet KPI Benchmarks
A1: KPI Benchmarks
A2: Single source of truth for every flag in this workbook. Edit column D to change thresholds.
A4: Stage | B4: Metric | C4: How it's calculated | D4: Threshold | E4: Rule | F4: If weak, usually… | G4: Fix
A5: Attention | B5: CTR (all) | C5: Clicks (all) ÷ Impressions | D5: 0.02 | E5: ≥ (aim for 3%+) | F5: Slow opening, generic first frame, brand-centric lead | G5: New hook or first visual
A6: Interest | B6: Link CTR ÷ CTR (all) | C6: Link CTR divided by CTR (all) | D6: 0.5 | E6: ≥ | F6: Entertaining but benefit unclear, weak offer | G6: Message, offer, CTA; run copy test
A7: Cost | B7: CPM ($) | C7: Spend ÷ Impressions × 1,000 | D7: 30 | E7: ≤ (new pixel $50–70) | F7: Expensive delivery | G7: Judge against CTR, never alone
A8: Page load | B8: Landing page views ÷ Link clicks | C8: LPV ÷ Link clicks | D8: 0.9 | E8: ≥ | F8: Slow page, tracking, accidental clicks, poor mobile | G8: Page speed and mobile first
A9: Buying intent | B9: Add-to-cart rate | C9: Adds to cart ÷ LPV | D9: 0.1 | E9: ≥ | F9: Ad promise not continued, price friction, no reviews/in-use photos | G9: Product page, social proof, bolder CTA, landing page test
A10: Cart | B10: Cart → checkout | C10: Checkouts ÷ Adds to cart | D10: 0.5 | E10: ≥ (lose ≤ 50%) | F10: Surprise shipping, upsell clutter, hidden mobile button | G10: Clean cart, show free shipping, stars near CTA
A11: Checkout | B11: Checkout → purchase | C11: Purchases ÷ Checkouts | D11: 0.5 | E11: ≥ (lose ≤ 50%) | F11: Payment options, trust, delivery time, no urgency | G11: 5%-off-24h BOF retargeting, more touchpoints
A12: Economics | B12: ROAS ÷ break-even ROAS | C12: ROAS ÷ Client Economics break-even | D12: 1 | E12: ≥ | F12: Cost per sale above what the margin allows | G12: Raise AOV first, then CPC / conversion
A13: Scale zone | B13: Scale-zone multiple | C13: Break-even ROAS × this = safe-to-scale ROAS | D13: 1.5 | E13: × | F13: — | G13: Scale in $10–20/day steps above this
A14: Creative test | B14: Impression cap per ad | C14: Rule: turn ad off above this | D14: 1000 | E14: impressions | F14: Judging ads on too little data | G14: 800 on new pixel with $50–70 CPM; 2–3k if budget allows
A16: Sources: benchmarks quoted in the videos (CTR 2–3%, link CTR ≥ 50% of CTR, CPM ~$28–30, ATC 10%, ≤ 50% drop per checkout step, 1,000-impression minimum).
A17: Assumptions (not stated in the videos): page-load ratio 90% ('small gap'); scale-zone multiple 1.5× break-even (video example: 1.67 break-even → scale above ~2.5–3x).

Sheet Client Economics
A1: Client Economics
A2: One row per client. Yellow = inputs. Break-even and budget structure calculate automatically.
A4: Client | B4: Goal | C4: AOV ($) | D4: Product cost / order ($) | E4: Fulfilment / order ($) | F4: Payment fees / order ($) | G4: Other variable cost / order ($) | H4: Margin per order ($) | I4: Break-even CPA ($) | J4: Break-even ROAS | K4: Scale-zone ROAS | L4: Target CPA ($) | M4: 12-month LTV ($) | N4: Max payback (days) | O4: Daily budget ($) | P4: Prospecting budget ($/day) | Q4: Retargeting budget ($/day) | R4: Max ads live | S4: Notes
A5: Example Outdoor Co | B5: Growth-first | C5: 100 | D5: 30 | E5: 5 | F5: 5 | G5: 0 | H5: =IF(C5="","",C5-SUM(D5:G5)) | I5: =IF(C5="","",H5) | J5: =IF(OR(C5="",H5<=0),"",C5/H5) | K5: =IF(J5="","",J5*'KPI Benchmarks'!$D$13) | L5: 30 | M5: 180 | N5: 60 | O5: 100 | P5: =IF(O5="","",O5*0.85) | Q5: =IF(O5="","",O5*0.15) | R5: =IF(O5="","",IF(O5<50,"1–3 ads",IF(O5<=700,"2–5 proven winners","5+ winners; weekly test batches"))) | S5: Video example: $100 order, $60 margin → 1.67x break-even
H6: =IF(C6="","",C6-SUM(D6:G6)) | I6: =IF(C6="","",H6) | J6: =IF(OR(C6="",H6<=0),"",C6/H6) | K6: =IF(J6="","",J6*'KPI Benchmarks'!$D$13) | P6: =IF(O6="","",O6*0.85) | Q6: =IF(O6="","",O6*0.15) | R6: =IF(O6="","",IF(O6<50,"1–3 ads",IF(O6<=700,"2–5 proven winners","5+ winners; weekly test batches")))
H7: =IF(C7="","",C7-SUM(D7:G7)) | I7: =IF(C7="","",H7) | J7: =IF(OR(C7="",H7<=0),"",C7/H7) | K7: =IF(J7="","",J7*'KPI Benchmarks'!$D$13) | P7: =IF(O7="","",O7*0.85) | Q7: =IF(O7="","",O7*0.15) | R7: =IF(O7="","",IF(O7<50,"1–3 ads",IF(O7<=700,"2–5 proven winners","5+ winners; weekly test batches")))
H8: =IF(C8="","",C8-SUM(D8:G8)) | I8: =IF(C8="","",H8) | J8: =IF(OR(C8="",H8<=0),"",C8/H8) | K8: =IF(J8="","",J8*'KPI Benchmarks'!$D$13) | P8: =IF(O8="","",O8*0.85) | Q8: =IF(O8="","",O8*0.15) | R8: =IF(O8="","",IF(O8<50,"1–3 ads",IF(O8<=700,"2–5 proven winners","5+ winners; weekly test batches")))
H9: =IF(C9="","",C9-SUM(D9:G9)) | I9: =IF(C9="","",H9) | J9: =IF(OR(C9="",H9<=0),"",C9/H9) | K9: =IF(J9="","",J9*'KPI Benchmarks'!$D$13) | P9: =IF(O9="","",O9*0.85) | Q9: =IF(O9="","",O9*0.15) | R9: =IF(O9="","",IF(O9<50,"1–3 ads",IF(O9<=700,"2–5 proven winners","5+ winners; weekly test batches")))
H10: =IF(C10="","",C10-SUM(D10:G10)) | I10: =IF(C10="","",H10) | J10: =IF(OR(C10="",H10<=0),"",C10/H10) | K10: =IF(J10="","",J10*'KPI Benchmarks'!$D$13) | P10: =IF(O10="","",O10*0.85) | Q10: =IF(O10="","",O10*0.15) | R10: =IF(O10="","",IF(O10<50,"1–3 ads",IF(O10<=700,"2–5 proven winners","5+ winners; weekly test batches")))
H11: =IF(C11="","",C11-SUM(D11:G11)) | I11: =IF(C11="","",H11) | J11: =IF(OR(C11="",H11<=0),"",C11/H11) | K11: =IF(J11="","",J11*'KPI Benchmarks'!$D$13) | P11: =IF(O11="","",O11*0.85) | Q11: =IF(O11="","",O11*0.15) | R11: =IF(O11="","",IF(O11<50,"1–3 ads",IF(O11<=700,"2–5 proven winners","5+ winners; weekly test batches")))
H12: =IF(C12="","",C12-SUM(D12:G12)) | I12: =IF(C12="","",H12) | J12: =IF(OR(C12="",H12<=0),"",C12/H12) | K12: =IF(J12="","",J12*'KPI Benchmarks'!$D$13) | P12: =IF(O12="","",O12*0.85) | Q12: =IF(O12="","",O12*0.15) | R12: =IF(O12="","",IF(O12<50,"1–3 ads",IF(O12<=700,"2–5 proven winners","5+ winners; weekly test batches")))
H13: =IF(C13="","",C13-SUM(D13:G13)) | I13: =IF(C13="","",H13) | J13: =IF(OR(C13="",H13<=0),"",C13/H13) | K13: =IF(J13="","",J13*'KPI Benchmarks'!$D$13) | P13: =IF(O13="","",O13*0.85) | Q13: =IF(O13="","",O13*0.15) | R13: =IF(O13="","",IF(O13<50,"1–3 ads",IF(O13<=700,"2–5 proven winners","5+ winners; weekly test batches")))
H14: =IF(C14="","",C14-SUM(D14:G14)) | I14: =IF(C14="","",H14) | J14: =IF(OR(C14="",H14<=0),"",C14/H14) | K14: =IF(J14="","",J14*'KPI Benchmarks'!$D$13) | P14: =IF(O14="","",O14*0.85) | Q14: =IF(O14="","",O14*0.15) | R14: =IF(O14="","",IF(O14<50,"1–3 ads",IF(O14<=700,"2–5 proven winners","5+ winners; weekly test batches")))
H15: =IF(C15="","",C15-SUM(D15:G15)) | I15: =IF(C15="","",H15) | J15: =IF(OR(C15="",H15<=0),"",C15/H15) | K15: =IF(J15="","",J15*'KPI Benchmarks'!$D$13) | P15: =IF(O15="","",O15*0.85) | Q15: =IF(O15="","",O15*0.15) | R15: =IF(O15="","",IF(O15<50,"1–3 ads",IF(O15<=700,"2–5 proven winners","5+ winners; weekly test batches")))
H16: =IF(C16="","",C16-SUM(D16:G16)) | I16: =IF(C16="","",H16) | J16: =IF(OR(C16="",H16<=0),"",C16/H16) | K16: =IF(J16="","",J16*'KPI Benchmarks'!$D$13) | P16: =IF(O16="","",O16*0.85) | Q16: =IF(O16="","",O16*0.15) | R16: =IF(O16="","",IF(O16<50,"1–3 ads",IF(O16<=700,"2–5 proven winners","5+ winners; weekly test batches")))
H17: =IF(C17="","",C17-SUM(D17:G17)) | I17: =IF(C17="","",H17) | J17: =IF(OR(C17="",H17<=0),"",C17/H17) | K17: =IF(J17="","",J17*'KPI Benchmarks'!$D$13) | P17: =IF(O17="","",O17*0.85) | Q17: =IF(O17="","",O17*0.15) | R17: =IF(O17="","",IF(O17<50,"1–3 ads",IF(O17<=700,"2–5 proven winners","5+ winners; weekly test batches")))
... H34: =IF(C34="","",C34-SUM(D34:G34)) | I34: =IF(C34="","",H34) | J34: =IF(OR(C34="",H34<=0),"",C34/H34) | K34: =IF(J34="","",J34*'KPI Benchmarks'!$D$13) | P34: =IF(O34="","",O34*0.85) | Q34: =IF(O34="","",O34*0.15) | R34: =IF(O34="","",IF(O34<50,"1–3 ads",IF(O34<=700,"2–5 proven winners","5+ winners; weekly test batches")))

Sheet Weekly Tracker
A1: Weekly Tracker
A2: One row per client per week (or per campaign). Paste Ads Manager + Shopify numbers into yellow columns; column Z names the first leak to fix.
A4: Week start | B4: Client | C4: Spend ($) | D4: Impressions | E4: Clicks (all) | F4: Link clicks | G4: Landing page views | H4: Adds to cart | I4: Checkouts initiated | J4: Purchases | K4: Revenue ($) | L4: CPM ($) | M4: CTR (all) | N4: Link CTR | O4: Link CTR ÷ CTR | P4: Cost per link click ($) | Q4: LPV ÷ link clicks | R4: Add-to-cart rate | S4: Cart → checkout | T4: Checkout → purchase | U4: ROAS | V4: CPA ($) | W4: AOV ($) | X4: Break-even ROAS | Y4: ROAS ÷ break-even | Z4: FIRST LEAK | AA4: What to fix | AB4: Notes / action taken
A5: 46279 | B5: Example Outdoor Co | C5: 700 | D5: 25000 | E5: 1000 | F5: 700 | G5: 640 | H5: 45 | I5: 20 | J5: 9 | K5: 1150 | L5: =IFERROR(C5/D5*1000,"") | M5: =IFERROR(E5/D5,"") | N5: =IFERROR(F5/D5,"") | O5: =IFERROR(N5/M5,"") | P5: =IFERROR(C5/F5,"") | Q5: =IFERROR(G5/F5,"") | R5: =IFERROR(H5/G5,"") | S5: =IFERROR(I5/H5,"") | T5: =IFERROR(J5/I5,"") | U5: =IFERROR(K5/C5,"") | V5: =IFERROR(C5/J5,"") | W5: =IFERROR(K5/J5,"") | X5: =IFERROR(INDEX('Client Economics'!$J$5:$J$34,MATCH(B5,'Client Economics'!$A$5:$A$34,0)),"") | Y5: =IFERROR(U5/X5,"") | Z5: =IF(D5="","",IF(N(M5)<'KPI Benchmarks'!$D$5,"Attention",IF(N(O5)<'KPI Benchmarks'!$D$6,"Interest",IF(N(Q5)<'KPI Benchmarks'!$D$8,"Page load",IF(N(R5)<'KPI Benchmarks'!$D$9,"Buying intent",IF(N(S5)<'KPI Benchmarks'!$D$10,"Cart",IF(N(T5)<'KPI Benchmarks'!$D$11,"Checkout",IF(X5="","Add economics",IF(N(Y5)<'KPI Benchmarks'!$D$12,"Economics","Healthy – scale"))))))))) | AA5: =IF(Z5="","",IF(Z5="Healthy – scale","All stages pass. Add $10–20/day or a new audience; test new creatives beside the main campaign.",IF(Z5="Add economics","Add this client to Client Economics.",IFERROR(INDEX('KPI Benchmarks'!$G$5:$G$12,MATCH(Z5,'KPI Benchmarks'!$A$5:$A$12,0)),"")))) | AB5: Example: ATC 7% < 10% → rework product page
L6: =IFERROR(C6/D6*1000,"") | M6: =IFERROR(E6/D6,"") | N6: =IFERROR(F6/D6,"") | O6: =IFERROR(N6/M6,"") | P6: =IFERROR(C6/F6,"") | Q6: =IFERROR(G6/F6,"") | R6: =IFERROR(H6/G6,"") | S6: =IFERROR(I6/H6,"") | T6: =IFERROR(J6/I6,"") | U6: =IFERROR(K6/C6,"") | V6: =IFERROR(C6/J6,"") | W6: =IFERROR(K6/J6,"") | X6: =IFERROR(INDEX('Client Economics'!$J$5:$J$34,MATCH(B6,'Client Economics'!$A$5:$A$34,0)),"") | Y6: =IFERROR(U6/X6,"") | Z6: =IF(D6="","",IF(N(M6)<'KPI Benchmarks'!$D$5,"Attention",IF(N(O6)<'KPI Benchmarks'!$D$6,"Interest",IF(N(Q6)<'KPI Benchmarks'!$D$8,"Page load",IF(N(R6)<'KPI Benchmarks'!$D$9,"Buying intent",IF(N(S6)<'KPI Benchmarks'!$D$10,"Cart",IF(N(T6)<'KPI Benchmarks'!$D$11,"Checkout",IF(X6="","Add economics",IF(N(Y6)<'KPI Benchmarks'!$D$12,"Economics","Healthy – scale"))))))))) | AA6: =IF(Z6="","",IF(Z6="Healthy – scale","All stages pass. Add $10–20/day or a new audience; test new creatives beside the main campaign.",IF(Z6="Add economics","Add this client to Client Economics.",IFERROR(INDEX('KPI Benchmarks'!$G$5:$G$12,MATCH(Z6,'KPI Benchmarks'!$A$5:$A$12,0)),""))))
L7: =IFERROR(C7/D7*1000,"") | M7: =IFERROR(E7/D7,"") | N7: =IFERROR(F7/D7,"") | O7: =IFERROR(N7/M7,"") | P7: =IFERROR(C7/F7,"") | Q7: =IFERROR(G7/F7,"") | R7: =IFERROR(H7/G7,"") | S7: =IFERROR(I7/H7,"") | T7: =IFERROR(J7/I7,"") | U7: =IFERROR(K7/C7,"") | V7: =IFERROR(C7/J7,"") | W7: =IFERROR(K7/J7,"") | X7: =IFERROR(INDEX('Client Economics'!$J$5:$J$34,MATCH(B7,'Client Economics'!$A$5:$A$34,0)),"") | Y7: =IFERROR(U7/X7,"") | Z7: =IF(D7="","",IF(N(M7)<'KPI Benchmarks'!$D$5,"Attention",IF(N(O7)<'KPI Benchmarks'!$D$6,"Interest",IF(N(Q7)<'KPI Benchmarks'!$D$8,"Page load",IF(N(R7)<'KPI Benchmarks'!$D$9,"Buying intent",IF(N(S7)<'KPI Benchmarks'!$D$10,"Cart",IF(N(T7)<'KPI Benchmarks'!$D$11,"Checkout",IF(X7="","Add economics",IF(N(Y7)<'KPI Benchmarks'!$D$12,"Economics","Healthy – scale"))))))))) | AA7: =IF(Z7="","",IF(Z7="Healthy – scale","All stages pass. Add $10–20/day or a new audience; test new creatives beside the main campaign.",IF(Z7="Add economics","Add this client to Client Economics.",IFERROR(INDEX('KPI Benchmarks'!$G$5:$G$12,MATCH(Z7,'KPI Benchmarks'!$A$5:$A$12,0)),""))))
L8: =IFERROR(C8/D8*1000,"") | M8: =IFERROR(E8/D8,"") | N8: =IFERROR(F8/D8,"") | O8: =IFERROR(N8/M8,"") | P8: =IFERROR(C8/F8,"") | Q8: =IFERROR(G8/F8,"") | R8: =IFERROR(H8/G8,"") | S8: =IFERROR(I8/H8,"") | T8: =IFERROR(J8/I8,"") | U8: =IFERROR(K8/C8,"") | V8: =IFERROR(C8/J8,"") | W8: =IFERROR(K8/J8,"") | X8: =IFERROR(INDEX('Client Economics'!$J$5:$J$34,MATCH(B8,'Client Economics'!$A$5:$A$34,0)),"") | Y8: =IFERROR(U8/X8,"") | Z8: =IF(D8="","",IF(N(M8)<'KPI Benchmarks'!$D$5,"Attention",IF(N(O8)<'KPI Benchmarks'!$D$6,"Interest",IF(N(Q8)<'KPI Benchmarks'!$D$8,"Page load",IF(N(R8)<'KPI Benchmarks'!$D$9,"Buying intent",IF(N(S8)<'KPI Benchmarks'!$D$10,"Cart",IF(N(T8)<'KPI Benchmarks'!$D$11,"Checkout",IF(X8="","Add economics",IF(N(Y8)<'KPI Benchmarks'!$D$12,"Economics","Healthy – scale"))))))))) | AA8: =IF(Z8="","",IF(Z8="Healthy – scale","All stages pass. Add $10–20/day or a new audience; test new creatives beside the main campaign.",IF(Z8="Add economics","Add this client to Client Economics.",IFERROR(INDEX('KPI Benchmarks'!$G$5:$G$12,MATCH(Z8,'KPI Benchmarks'!$A$5:$A$12,0)),""))))
L9: =IFERROR(C9/D9*1000,"") | M9: =IFERROR(E9/D9,"") | N9: =IFERROR(F9/D9,"") | O9: =IFERROR(N9/M9,"") | P9: =IFERROR(C9/F9,"") | Q9: =IFERROR(G9/F9,"") | R9: =IFERROR(H9/G9,"") | S9: =IFERROR(I9/H9,"") | T9: =IFERROR(J9/I9,"") | U9: =IFERROR(K9/C9,"") | V9: =IFERROR(C9/J9,"") | W9: =IFERROR(K9/J9,"") | X9: =IFERROR(INDEX('Client Economics'!$J$5:$J$34,MATCH(B9,'Client Economics'!$A$5:$A$34,0)),"") | Y9: =IFERROR(U9/X9,"") | Z9: =IF(D9="","",IF(N(M9)<'KPI Benchmarks'!$D$5,"Attention",IF(N(O9)<'KPI Benchmarks'!$D$6,"Interest",IF(N(Q9)<'KPI Benchmarks'!$D$8,"Page load",IF(N(R9)<'KPI Benchmarks'!$D$9,"Buying intent",IF(N(S9)<'KPI Benchmarks'!$D$10,"Cart",IF(N(T9)<'KPI Benchmarks'!$D$11,"Checkout",IF(X9="","Add economics",IF(N(Y9)<'KPI Benchmarks'!$D$12,"Economics","Healthy – scale"))))))))) | AA9: =IF(Z9="","",IF(Z9="Healthy – scale","All stages pass. Add $10–20/day or a new audience; test new creatives beside the main campaign.",IF(Z9="Add economics","Add this client to Client Economics.",IFERROR(INDEX('KPI Benchmarks'!$G$5:$G$12,MATCH(Z9,'KPI Benchmarks'!$A$5:$A$12,0)),""))))
L10: =IFERROR(C10/D10*1000,"") | M10: =IFERROR(E10/D10,"") | N10: =IFERROR(F10/D10,"") | O10: =IFERROR(N10/M10,"") | P10: =IFERROR(C10/F10,"") | Q10: =IFERROR(G10/F10,"") | R10: =IFERROR(H10/G10,"") | S10: =IFERROR(I10/H10,"") | T10: =IFERROR(J10/I10,"") | U10: =IFERROR(K10/C10,"") | V10: =IFERROR(C10/J10,"") | W10: =IFERROR(K10/J10,"") | X10: =IFERROR(INDEX('Client Economics'!$J$5:$J$34,MATCH(B10,'Client Economics'!$A$5:$A$34,0)),"") | Y10: =IFERROR(U10/X10,"") | Z10: =IF(D10="","",IF(N(M10)<'KPI Benchmarks'!$D$5,"Attention",IF(N(O10)<'KPI Benchmarks'!$D$6,"Interest",IF(N(Q10)<'KPI Benchmarks'!$D$8,"Page load",IF(N(R10)<'KPI Benchmarks'!$D$9,"Buying intent",IF(N(S10)<'KPI Benchmarks'!$D$10,"Cart",IF(N(T10)<'KPI Benchmarks'!$D$11,"Checkout",IF(X10="","Add economics",IF(N(Y10)<'KPI Benchmarks'!$D$12,"Economics","Healthy – scale"))))))))) | AA10: =IF(Z10="","",IF(Z10="Healthy – scale","All stages pass. Add $10–20/day or a new audience; test new creatives beside the main campaign.",IF(Z10="Add economics","Add this client to Client Economics.",IFERROR(INDEX('KPI Benchmarks'!$G$5:$G$12,MATCH(Z10,'KPI Benchmarks'!$A$5:$A$12,0)),""))))
L11: =IFERROR(C11/D11*1000,"") | M11: =IFERROR(E11/D11,"") | N11: =IFERROR(F11/D11,"") | O11: =IFERROR(N11/M11,"") | P11: =IFERROR(C11/F11,"") | Q11: =IFERROR(G11/F11,"") | R11: =IFERROR(H11/G11,"") | S11: =IFERROR(I11/H11,"") | T11: =IFERROR(J11/I11,"") | U11: =IFERROR(K11/C11,"") | V11: =IFERROR(C11/J11,"") | W11: =IFERROR(K11/J11,"") | X11: =IFERROR(INDEX('Client Economics'!$J$5:$J$34,MATCH(B11,'Client Economics'!$A$5:$A$34,0)),"") | Y11: =IFERROR(U11/X11,"") | Z11: =IF(D11="","",IF(N(M11)<'KPI Benchmarks'!$D$5,"Attention",IF(N(O11)<'KPI Benchmarks'!$D$6,"Interest",IF(N(Q11)<'KPI Benchmarks'!$D$8,"Page load",IF(N(R11)<'KPI Benchmarks'!$D$9,"Buying intent",IF(N(S11)<'KPI Benchmarks'!$D$10,"Cart",IF(N(T11)<'KPI Benchmarks'!$D$11,"Checkout",IF(X11="","Add economics",IF(N(Y11)<'KPI Benchmarks'!$D$12,"Economics","Healthy – scale"))))))))) | AA11: =IF(Z11="","",IF(Z11="Healthy – scale","All stages pass. Add $10–20/day or a new audience; test new creatives beside the main campaign.",IF(Z11="Add economics","Add this client to Client Economics.",IFERROR(INDEX('KPI Benchmarks'!$G$5:$G$12,MATCH(Z11,'KPI Benchmarks'!$A$5:$A$12,0)),""))))
L12: =IFERROR(C12/D12*1000,"") | M12: =IFERROR(E12/D12,"") | N12: =IFERROR(F12/D12,"") | O12: =IFERROR(N12/M12,"") | P12: =IFERROR(C12/F12,"") | Q12: =IFERROR(G12/F12,"") | R12: =IFERROR(H12/G12,"") | S12: =IFERROR(I12/H12,"") | T12: =IFERROR(J12/I12,"") | U12: =IFERROR(K12/C12,"") | V12: =IFERROR(C12/J12,"") | W12: =IFERROR(K12/J12,"") | X12: =IFERROR(INDEX('Client Economics'!$J$5:$J$34,MATCH(B12,'Client Economics'!$A$5:$A$34,0)),"") | Y12: =IFERROR(U12/X12,"") | Z12: =IF(D12="","",IF(N(M12)<'KPI Benchmarks'!$D$5,"Attention",IF(N(O12)<'KPI Benchmarks'!$D$6,"Interest",IF(N(Q12)<'KPI Benchmarks'!$D$8,"Page load",IF(N(R12)<'KPI Benchmarks'!$D$9,"Buying intent",IF(N(S12)<'KPI Benchmarks'!$D$10,"Cart",IF(N(T12)<'KPI Benchmarks'!$D$11,"Checkout",IF(X12="","Add economics",IF(N(Y12)<'KPI Benchmarks'!$D$12,"Economics","Healthy – scale"))))))))) | AA12: =IF(Z12="","",IF(Z12="Healthy – scale","All stages pass. Add $10–20/day or a new audience; test new creatives beside the main campaign.",IF(Z12="Add economics","Add this client to Client Economics.",IFERROR(INDEX('KPI Benchmarks'!$G$5:$G$12,MATCH(Z12,'KPI Benchmarks'!$A$5:$A$12,0)),""))))
L13: =IFERROR(C13/D13*1000,"") | M13: =IFERROR(E13/D13,"") | N13: =IFERROR(F13/D13,"") | O13: =IFERROR(N13/M13,"") | P13: =IFERROR(C13/F13,"") | Q13: =IFERROR(G13/F13,"") | R13: =IFERROR(H13/G13,"") | S13: =IFERROR(I13/H13,"") | T13: =IFERROR(J13/I13,"") | U13: =IFERROR(K13/C13,"") | V13: =IFERROR(C13/J13,"") | W13: =IFERROR(K13/J13,"") | X13: =IFERROR(INDEX('Client Economics'!$J$5:$J$34,MATCH(B13,'Client Economics'!$A$5:$A$34,0)),"") | Y13: =IFERROR(U13/X13,"") | Z13: =IF(D13="","",IF(N(M13)<'KPI Benchmarks'!$D$5,"Attention",IF(N(O13)<'KPI Benchmarks'!$D$6,"Interest",IF(N(Q13)<'KPI Benchmarks'!$D$8,"Page load",IF(N(R13)<'KPI Benchmarks'!$D$9,"Buying intent",IF(N(S13)<'KPI Benchmarks'!$D$10,"Cart",IF(N(T13)<'KPI Benchmarks'!$D$11,"Checkout",IF(X13="","Add economics",IF(N(Y13)<'KPI Benchmarks'!$D$12,"Economics","Healthy – scale"))))))))) | AA13: =IF(Z13="","",IF(Z13="Healthy – scale","All stages pass. Add $10–20/day or a new audience; test new creatives beside the main campaign.",IF(Z13="Add economics","Add this client to Client Economics.",IFERROR(INDEX('KPI Benchmarks'!$G$5:$G$12,MATCH(Z13,'KPI Benchmarks'!$A$5:$A$12,0)),""))))
L14: =IFERROR(C14/D14*1000,"") | M14: =IFERROR(E14/D14,"") | N14: =IFERROR(F14/D14,"") | O14: =IFERROR(N14/M14,"") | P14: =IFERROR(C14/F14,"") | Q14: =IFERROR(G14/F14,"") | R14: =IFERROR(H14/G14,"") | S14: =IFERROR(I14/H14,"") | T14: =IFERROR(J14/I14,"") | U14: =IFERROR(K14/C14,"") | V14: =IFERROR(C14/J14,"") | W14: =IFERROR(K14/J14,"") | X14: =IFERROR(INDEX('Client Economics'!$J$5:$J$34,MATCH(B14,'Client Economics'!$A$5:$A$34,0)),"") | Y14: =IFERROR(U14/X14,"") | Z14: =IF(D14="","",IF(N(M14)<'KPI Benchmarks'!$D$5,"Attention",IF(N(O14)<'KPI Benchmarks'!$D$6,"Interest",IF(N(Q14)<'KPI Benchmarks'!$D$8,"Page load",IF(N(R14)<'KPI Benchmarks'!$D$9,"Buying intent",IF(N(S14)<'KPI Benchmarks'!$D$10,"Cart",IF(N(T14)<'KPI Benchmarks'!$D$11,"Checkout",IF(X14="","Add economics",IF(N(Y14)<'KPI Benchmarks'!$D$12,"Economics","Healthy – scale"))))))))) | AA14: =IF(Z14="","",IF(Z14="Healthy – scale","All stages pass. Add $10–20/day or a new audience; test new creatives beside the main campaign.",IF(Z14="Add economics","Add this client to Client Economics.",IFERROR(INDEX('KPI Benchmarks'!$G$5:$G$12,MATCH(Z14,'KPI Benchmarks'!$A$5:$A$12,0)),""))))
L15: =IFERROR(C15/D15*1000,"") | M15: =IFERROR(E15/D15,"") | N15: =IFERROR(F15/D15,"") | O15: =IFERROR(N15/M15,"") | P15: =IFERROR(C15/F15,"") | Q15: =IFERROR(G15/F15,"") | R15: =IFERROR(H15/G15,"") | S15: =IFERROR(I15/H15,"") | T15: =IFERROR(J15/I15,"") | U15: =IFERROR(K15/C15,"") | V15: =IFERROR(C15/J15,"") | W15: =IFERROR(K15/J15,"") | X15: =IFERROR(INDEX('Client Economics'!$J$5:$J$34,MATCH(B15,'Client Economics'!$A$5:$A$34,0)),"") | Y15: =IFERROR(U15/X15,"") | Z15: =IF(D15="","",IF(N(M15)<'KPI Benchmarks'!$D$5,"Attention",IF(N(O15)<'KPI Benchmarks'!$D$6,"Interest",IF(N(Q15)<'KPI Benchmarks'!$D$8,"Page load",IF(N(R15)<'KPI Benchmarks'!$D$9,"Buying intent",IF(N(S15)<'KPI Benchmarks'!$D$10,"Cart",IF(N(T15)<'KPI Benchmarks'!$D$11,"Checkout",IF(X15="","Add economics",IF(N(Y15)<'KPI Benchmarks'!$D$12,"Economics","Healthy – scale"))))))))) | AA15: =IF(Z15="","",IF(Z15="Healthy – scale","All stages pass. Add $10–20/day or a new audience; test new creatives beside the main campaign.",IF(Z15="Add economics","Add this client to Client Economics.",IFERROR(INDEX('KPI Benchmarks'!$G$5:$G$12,MATCH(Z15,'KPI Benchmarks'!$A$5:$A$12,0)),""))))
L16: =IFERROR(C16/D16*1000,"") | M16: =IFERROR(E16/D16,"") | N16: =IFERROR(F16/D16,"") | O16: =IFERROR(N16/M16,"") | P16: =IFERROR(C16/F16,"") | Q16: =IFERROR(G16/F16,"") | R16: =IFERROR(H16/G16,"") | S16: =IFERROR(I16/H16,"") | T16: =IFERROR(J16/I16,"") | U16: =IFERROR(K16/C16,"") | V16: =IFERROR(C16/J16,"") | W16: =IFERROR(K16/J16,"") | X16: =IFERROR(INDEX('Client Economics'!$J$5:$J$34,MATCH(B16,'Client Economics'!$A$5:$A$34,0)),"") | Y16: =IFERROR(U16/X16,"") | Z16: =IF(D16="","",IF(N(M16)<'KPI Benchmarks'!$D$5,"Attention",IF(N(O16)<'KPI Benchmarks'!$D$6,"Interest",IF(N(Q16)<'KPI Benchmarks'!$D$8,"Page load",IF(N(R16)<'KPI Benchmarks'!$D$9,"Buying intent",IF(N(S16)<'KPI Benchmarks'!$D$10,"Cart",IF(N(T16)<'KPI Benchmarks'!$D$11,"Checkout",IF(X16="","Add economics",IF(N(Y16)<'KPI Benchmarks'!$D$12,"Economics","Healthy – scale"))))))))) | AA16: =IF(Z16="","",IF(Z16="Healthy – scale","All stages pass. Add $10–20/day or a new audience; test new creatives beside the main campaign.",IF(Z16="Add economics","Add this client to Client Economics.",IFERROR(INDEX('KPI Benchmarks'!$G$5:$G$12,MATCH(Z16,'KPI Benchmarks'!$A$5:$A$12,0)),""))))
L17: =IFERROR(C17/D17*1000,"") | M17: =IFERROR(E17/D17,"") | N17: =IFERROR(F17/D17,"") | O17: =IFERROR(N17/M17,"") | P17: =IFERROR(C17/F17,"") | Q17: =IFERROR(G17/F17,"") | R17: =IFERROR(H17/G17,"") | S17: =IFERROR(I17/H17,"") | T17: =IFERROR(J17/I17,"") | U17: =IFERROR(K17/C17,"") | V17: =IFERROR(C17/J17,"") | W17: =IFERROR(K17/J17,"") | X17: =IFERROR(INDEX('Client Economics'!$J$5:$J$34,MATCH(B17,'Client Economics'!$A$5:$A$34,0)),"") | Y17: =IFERROR(U17/X17,"") | Z17: =IF(D17="","",IF(N(M17)<'KPI Benchmarks'!$D$5,"Attention",IF(N(O17)<'KPI Benchmarks'!$D$6,"Interest",IF(N(Q17)<'KPI Benchmarks'!$D$8,"Page load",IF(N(R17)<'KPI Benchmarks'!$D$9,"Buying intent",IF(N(S17)<'KPI Benchmarks'!$D$10,"Cart",IF(N(T17)<'KPI Benchmarks'!$D$11,"Checkout",IF(X17="","Add economics",IF(N(Y17)<'KPI Benchmarks'!$D$12,"Economics","Healthy – scale"))))))))) | AA17: =IF(Z17="","",IF(Z17="Healthy – scale","All stages pass. Add $10–20/day or a new audience; test new creatives beside the main campaign.",IF(Z17="Add economics","Add this client to Client Economics.",IFERROR(INDEX('KPI Benchmarks'!$G$5:$G$12,MATCH(Z17,'KPI Benchmarks'!$A$5:$A$12,0)),""))))
... L203: =IFERROR(C203/D203*1000,"") | M203: =IFERROR(E203/D203,"") | N203: =IFERROR(F203/D203,"") | O203: =IFERROR(N203/M203,"") | P203: =IFERROR(C203/F203,"") | Q203: =IFERROR(G203/F203,"") | R203: =IFERROR(H203/G203,"") | S203: =IFERROR(I203/H203,"") | T203: =IFERROR(J203/I203,"") | U203: =IFERROR(K203/C203,"") | V203: =IFERROR(C203/J203,"") | W203: =IFERROR(K203/J203,"") | X203: =IFERROR(INDEX('Client Economics'!$J$5:$J$34,MATCH(B203,'Client Economics'!$A$5:$A$34,0)),"") | Y203: =IFERROR(U203/X203,"") | Z203: =IF(D203="","",IF(N(M203)<'KPI Benchmarks'!$D$5,"Attention",IF(N(O203)<'KPI Benchmarks'!$D$6,"Interest",IF(N(Q203)<'KPI Benchmarks'!$D$8,"Page load",IF(N(R203)<'KPI Benchmarks'!$D$9,"Buying intent",IF(N(S203)<'KPI Benchmarks'!$D$10,"Cart",IF(N(T203)<'KPI Benchmarks'!$D$11,"Checkout",IF(X203="","Add economics",IF(N(Y203)<'KPI Benchmarks'!$D$12,"Economics","Healthy – scale"))))))))) | AA203: =IF(Z203="","",IF(Z203="Healthy – scale","All stages pass. Add $10–20/day or a new audience; test new creatives beside the main campaign.",IF(Z203="Add economics","Add this client to Client Economics.",IFERROR(INDEX('KPI Benchmarks'!$G$5:$G$12,MATCH(Z203,'KPI Benchmarks'!$A$5:$A$12,0)),""))))

Sheet Creative Test Log
A1: Creative Test Log
A2: Step 1 of the stairway. One row per ad. Verdict is automatic once an ad reaches the impression cap (KPI Benchmarks D14).
A4: Client | B4: Test ID | C4: Ad name | D4: Format | E4: Angle (one sentence) | F4: Hook (first 3 seconds) | G4: Impressions | H4: Spend ($) | I4: Clicks (all) | J4: Link clicks | K4: Adds to cart | L4: Purchases | M4: Revenue ($) | N4: CPM ($) | O4: CTR (all) | P4: Link CTR | Q4: Link CTR ÷ CTR | R4: ATC ÷ link clicks | S4: ROAS | T4: Reached cap? | U4: VERDICT | V4: Suggested role | W4: Why it won / lost (for next brief)
A5: Example Outdoor Co | B5: CT-01 | C5: Unboxing – eczema mum | D5: Unboxing | E5: Toxic-free relief for kids' eczema | F5: Box opening; 'my boys had eczema…' | G5: 1020 | H5: 31 | I5: 64 | J5: 36 | K5: 5 | L5: 2 | M5: 118 | N5: =IFERROR(H5/G5*1000,"") | O5: =IFERROR(I5/G5,"") | P5: =IFERROR(J5/G5,"") | Q5: =IFERROR(P5/O5,"") | R5: =IFERROR(K5/J5,"") | S5: =IFERROR(M5/H5,"") | T5: =IF(G5="","",IF(G5>='KPI Benchmarks'!$D$14,"Yes","No")) | U5: =IF(G5="","",IF(T5="No","Running",IF(AND(N(O5)>='KPI Benchmarks'!$D$5,N(Q5)>='KPI Benchmarks'!$D$6,OR(N(L5)>0,N(K5)>0)),"WINNER",IF(AND(N(O5)>='KPI Benchmarks'!$D$5,N(Q5)>='KPI Benchmarks'!$D$6),"Watch","Cut")))) | V5: =IF(U5="WINNER",IF(N(L5)>0,"Prospecting (ASC / interests)","Retargeting candidate"),IF(U5="Watch","Retest or retargeting","" )) | W5: Box-about-to-open hook + emotional pain point; UGC feel builds trust
N6: =IFERROR(H6/G6*1000,"") | O6: =IFERROR(I6/G6,"") | P6: =IFERROR(J6/G6,"") | Q6: =IFERROR(P6/O6,"") | R6: =IFERROR(K6/J6,"") | S6: =IFERROR(M6/H6,"") | T6: =IF(G6="","",IF(G6>='KPI Benchmarks'!$D$14,"Yes","No")) | U6: =IF(G6="","",IF(T6="No","Running",IF(AND(N(O6)>='KPI Benchmarks'!$D$5,N(Q6)>='KPI Benchmarks'!$D$6,OR(N(L6)>0,N(K6)>0)),"WINNER",IF(AND(N(O6)>='KPI Benchmarks'!$D$5,N(Q6)>='KPI Benchmarks'!$D$6),"Watch","Cut")))) | V6: =IF(U6="WINNER",IF(N(L6)>0,"Prospecting (ASC / interests)","Retargeting candidate"),IF(U6="Watch","Retest or retargeting","" ))
N7: =IFERROR(H7/G7*1000,"") | O7: =IFERROR(I7/G7,"") | P7: =IFERROR(J7/G7,"") | Q7: =IFERROR(P7/O7,"") | R7: =IFERROR(K7/J7,"") | S7: =IFERROR(M7/H7,"") | T7: =IF(G7="","",IF(G7>='KPI Benchmarks'!$D$14,"Yes","No")) | U7: =IF(G7="","",IF(T7="No","Running",IF(AND(N(O7)>='KPI Benchmarks'!$D$5,N(Q7)>='KPI Benchmarks'!$D$6,OR(N(L7)>0,N(K7)>0)),"WINNER",IF(AND(N(O7)>='KPI Benchmarks'!$D$5,N(Q7)>='KPI Benchmarks'!$D$6),"Watch","Cut")))) | V7: =IF(U7="WINNER",IF(N(L7)>0,"Prospecting (ASC / interests)","Retargeting candidate"),IF(U7="Watch","Retest or retargeting","" ))
N8: =IFERROR(H8/G8*1000,"") | O8: =IFERROR(I8/G8,"") | P8: =IFERROR(J8/G8,"") | Q8: =IFERROR(P8/O8,"") | R8: =IFERROR(K8/J8,"") | S8: =IFERROR(M8/H8,"") | T8: =IF(G8="","",IF(G8>='KPI Benchmarks'!$D$14,"Yes","No")) | U8: =IF(G8="","",IF(T8="No","Running",IF(AND(N(O8)>='KPI Benchmarks'!$D$5,N(Q8)>='KPI Benchmarks'!$D$6,OR(N(L8)>0,N(K8)>0)),"WINNER",IF(AND(N(O8)>='KPI Benchmarks'!$D$5,N(Q8)>='KPI Benchmarks'!$D$6),"Watch","Cut")))) | V8: =IF(U8="WINNER",IF(N(L8)>0,"Prospecting (ASC / interests)","Retargeting candidate"),IF(U8="Watch","Retest or retargeting","" ))
N9: =IFERROR(H9/G9*1000,"") | O9: =IFERROR(I9/G9,"") | P9: =IFERROR(J9/G9,"") | Q9: =IFERROR(P9/O9,"") | R9: =IFERROR(K9/J9,"") | S9: =IFERROR(M9/H9,"") | T9: =IF(G9="","",IF(G9>='KPI Benchmarks'!$D$14,"Yes","No")) | U9: =IF(G9="","",IF(T9="No","Running",IF(AND(N(O9)>='KPI Benchmarks'!$D$5,N(Q9)>='KPI Benchmarks'!$D$6,OR(N(L9)>0,N(K9)>0)),"WINNER",IF(AND(N(O9)>='KPI Benchmarks'!$D$5,N(Q9)>='KPI Benchmarks'!$D$6),"Watch","Cut")))) | V9: =IF(U9="WINNER",IF(N(L9)>0,"Prospecting (ASC / interests)","Retargeting candidate"),IF(U9="Watch","Retest or retargeting","" ))
N10: =IFERROR(H10/G10*1000,"") | O10: =IFERROR(I10/G10,"") | P10: =IFERROR(J10/G10,"") | Q10: =IFERROR(P10/O10,"") | R10: =IFERROR(K10/J10,"") | S10: =IFERROR(M10/H10,"") | T10: =IF(G10="","",IF(G10>='KPI Benchmarks'!$D$14,"Yes","No")) | U10: =IF(G10="","",IF(T10="No","Running",IF(AND(N(O10)>='KPI Benchmarks'!$D$5,N(Q10)>='KPI Benchmarks'!$D$6,OR(N(L10)>0,N(K10)>0)),"WINNER",IF(AND(N(O10)>='KPI Benchmarks'!$D$5,N(Q10)>='KPI Benchmarks'!$D$6),"Watch","Cut")))) | V10: =IF(U10="WINNER",IF(N(L10)>0,"Prospecting (ASC / interests)","Retargeting candidate"),IF(U10="Watch","Retest or retargeting","" ))
N11: =IFERROR(H11/G11*1000,"") | O11: =IFERROR(I11/G11,"") | P11: =IFERROR(J11/G11,"") | Q11: =IFERROR(P11/O11,"") | R11: =IFERROR(K11/J11,"") | S11: =IFERROR(M11/H11,"") | T11: =IF(G11="","",IF(G11>='KPI Benchmarks'!$D$14,"Yes","No")) | U11: =IF(G11="","",IF(T11="No","Running",IF(AND(N(O11)>='KPI Benchmarks'!$D$5,N(Q11)>='KPI Benchmarks'!$D$6,OR(N(L11)>0,N(K11)>0)),"WINNER",IF(AND(N(O11)>='KPI Benchmarks'!$D$5,N(Q11)>='KPI Benchmarks'!$D$6),"Watch","Cut")))) | V11: =IF(U11="WINNER",IF(N(L11)>0,"Prospecting (ASC / interests)","Retargeting candidate"),IF(U11="Watch","Retest or retargeting","" ))
N12: =IFERROR(H12/G12*1000,"") | O12: =IFERROR(I12/G12,"") | P12: =IFERROR(J12/G12,"") | Q12: =IFERROR(P12/O12,"") | R12: =IFERROR(K12/J12,"") | S12: =IFERROR(M12/H12,"") | T12: =IF(G12="","",IF(G12>='KPI Benchmarks'!$D$14,"Yes","No")) | U12: =IF(G12="","",IF(T12="No","Running",IF(AND(N(O12)>='KPI Benchmarks'!$D$5,N(Q12)>='KPI Benchmarks'!$D$6,OR(N(L12)>0,N(K12)>0)),"WINNER",IF(AND(N(O12)>='KPI Benchmarks'!$D$5,N(Q12)>='KPI Benchmarks'!$D$6),"Watch","Cut")))) | V12: =IF(U12="WINNER",IF(N(L12)>0,"Prospecting (ASC / interests)","Retargeting candidate"),IF(U12="Watch","Retest or retargeting","" ))
N13: =IFERROR(H13/G13*1000,"") | O13: =IFERROR(I13/G13,"") | P13: =IFERROR(J13/G13,"") | Q13: =IFERROR(P13/O13,"") | R13: =IFERROR(K13/J13,"") | S13: =IFERROR(M13/H13,"") | T13: =IF(G13="","",IF(G13>='KPI Benchmarks'!$D$14,"Yes","No")) | U13: =IF(G13="","",IF(T13="No","Running",IF(AND(N(O13)>='KPI Benchmarks'!$D$5,N(Q13)>='KPI Benchmarks'!$D$6,OR(N(L13)>0,N(K13)>0)),"WINNER",IF(AND(N(O13)>='KPI Benchmarks'!$D$5,N(Q13)>='KPI Benchmarks'!$D$6),"Watch","Cut")))) | V13: =IF(U13="WINNER",IF(N(L13)>0,"Prospecting (ASC / interests)","Retargeting candidate"),IF(U13="Watch","Retest or retargeting","" ))
N14: =IFERROR(H14/G14*1000,"") | O14: =IFERROR(I14/G14,"") | P14: =IFERROR(J14/G14,"") | Q14: =IFERROR(P14/O14,"") | R14: =IFERROR(K14/J14,"") | S14: =IFERROR(M14/H14,"") | T14: =IF(G14="","",IF(G14>='KPI Benchmarks'!$D$14,"Yes","No")) | U14: =IF(G14="","",IF(T14="No","Running",IF(AND(N(O14)>='KPI Benchmarks'!$D$5,N(Q14)>='KPI Benchmarks'!$D$6,OR(N(L14)>0,N(K14)>0)),"WINNER",IF(AND(N(O14)>='KPI Benchmarks'!$D$5,N(Q14)>='KPI Benchmarks'!$D$6),"Watch","Cut")))) | V14: =IF(U14="WINNER",IF(N(L14)>0,"Prospecting (ASC / interests)","Retargeting candidate"),IF(U14="Watch","Retest or retargeting","" ))
N15: =IFERROR(H15/G15*1000,"") | O15: =IFERROR(I15/G15,"") | P15: =IFERROR(J15/G15,"") | Q15: =IFERROR(P15/O15,"") | R15: =IFERROR(K15/J15,"") | S15: =IFERROR(M15/H15,"") | T15: =IF(G15="","",IF(G15>='KPI Benchmarks'!$D$14,"Yes","No")) | U15: =IF(G15="","",IF(T15="No","Running",IF(AND(N(O15)>='KPI Benchmarks'!$D$5,N(Q15)>='KPI Benchmarks'!$D$6,OR(N(L15)>0,N(K15)>0)),"WINNER",IF(AND(N(O15)>='KPI Benchmarks'!$D$5,N(Q15)>='KPI Benchmarks'!$D$6),"Watch","Cut")))) | V15: =IF(U15="WINNER",IF(N(L15)>0,"Prospecting (ASC / interests)","Retargeting candidate"),IF(U15="Watch","Retest or retargeting","" ))
N16: =IFERROR(H16/G16*1000,"") | O16: =IFERROR(I16/G16,"") | P16: =IFERROR(J16/G16,"") | Q16: =IFERROR(P16/O16,"") | R16: =IFERROR(K16/J16,"") | S16: =IFERROR(M16/H16,"") | T16: =IF(G16="","",IF(G16>='KPI Benchmarks'!$D$14,"Yes","No")) | U16: =IF(G16="","",IF(T16="No","Running",IF(AND(N(O16)>='KPI Benchmarks'!$D$5,N(Q16)>='KPI Benchmarks'!$D$6,OR(N(L16)>0,N(K16)>0)),"WINNER",IF(AND(N(O16)>='KPI Benchmarks'!$D$5,N(Q16)>='KPI Benchmarks'!$D$6),"Watch","Cut")))) | V16: =IF(U16="WINNER",IF(N(L16)>0,"Prospecting (ASC / interests)","Retargeting candidate"),IF(U16="Watch","Retest or retargeting","" ))
N17: =IFERROR(H17/G17*1000,"") | O17: =IFERROR(I17/G17,"") | P17: =IFERROR(J17/G17,"") | Q17: =IFERROR(P17/O17,"") | R17: =IFERROR(K17/J17,"") | S17: =IFERROR(M17/H17,"") | T17: =IF(G17="","",IF(G17>='KPI Benchmarks'!$D$14,"Yes","No")) | U17: =IF(G17="","",IF(T17="No","Running",IF(AND(N(O17)>='KPI Benchmarks'!$D$5,N(Q17)>='KPI Benchmarks'!$D$6,OR(N(L17)>0,N(K17)>0)),"WINNER",IF(AND(N(O17)>='KPI Benchmarks'!$D$5,N(Q17)>='KPI Benchmarks'!$D$6),"Watch","Cut")))) | V17: =IF(U17="WINNER",IF(N(L17)>0,"Prospecting (ASC / interests)","Retargeting candidate"),IF(U17="Watch","Retest or retargeting","" ))
... N304: =IFERROR(H304/G304*1000,"") | O304: =IFERROR(I304/G304,"") | P304: =IFERROR(J304/G304,"") | Q304: =IFERROR(P304/O304,"") | R304: =IFERROR(K304/J304,"") | S304: =IFERROR(M304/H304,"") | T304: =IF(G304="","",IF(G304>='KPI Benchmarks'!$D$14,"Yes","No")) | U304: =IF(G304="","",IF(T304="No","Running",IF(AND(N(O304)>='KPI Benchmarks'!$D$5,N(Q304)>='KPI Benchmarks'!$D$6,OR(N(L304)>0,N(K304)>0)),"WINNER",IF(AND(N(O304)>='KPI Benchmarks'!$D$5,N(Q304)>='KPI Benchmarks'!$D$6),"Watch","Cut")))) | V304: =IF(U304="WINNER",IF(N(L304)>0,"Prospecting (ASC / interests)","Retargeting candidate"),IF(U304="Watch","Retest or retargeting","" ))

Sheet Stairway Test Log
A1: Stairway Test Log
A2: Every test beyond the creative test. One variable per row; everything else held constant.
A4: Client | B4: Step | C4: Variable tested | D4: Held constant | E4: Variants | F4: Structure / budget | G4: Start | H4: End | I4: Status | J4: Winner | K4: Deciding metric | L4: Learning → next brief
A5: Example Outdoor Co | B5: 3 Landing page | C5: Destination URL | D5: Winning ad + original copy, broad | E5: Home · Collection · Product · Custom persona page | F5: ABO, 1 URL per ad set, ~$100 each | G5: 46266 | H5: 46273 | I5: Done | J5: Custom persona page | K5: Most carts reaching purchase; ROAS | L5: Build a second persona page for truckers
